octoq/__init__.py
octoq-1.0.1.dist-info/METADATA
octoq-1.0.1.dist-info/WHEEL
octoq-1.0.1.dist-info/licenses/LICENSE
octoq-1.0.1.dist-info/RECORD
