Metadata-Version: 2.4
Name: octoq
Version: 1.0.1
Summary: A quantum computation package
Author-email: cgl <cuigl@arclightquantum.com>
License-File: LICENSE
Keywords: quantum computation
Requires-Python: >=3.8
Requires-Dist: numpy
